stratpy-0.0.4.dist-info/METADATA
stratpy-0.0.4.dist-info/WHEEL
stratpy-0.0.4.dist-info/license_files/LICENSE
stratpy/__init__.py
stratpy/__init__.pyi
stratpy/py.typed
stratpy/stratpy.cp311-win_amd64.pyd
stratpy-0.0.4.dist-info/RECORD
