Metadata-Version: 2.1
Name: stratpy
Version: 0.0.4
Classifier: Programming Language :: Rust
Classifier: Programming Language :: Python :: Implementation :: CPython
Classifier: Programming Language :: Python :: Implementation :: PyPy
License-File: LICENSE
Summary: Rust based Game Theory package
Author: Fredrik Ofstad
Requires-Python: >=3.7
